PyOps/__init__.py
PyOps/pyOps.py
pythonOps-0.1.4.dist-info/METADATA
pythonOps-0.1.4.dist-info/WHEEL
pythonOps-0.1.4.dist-info/entry_points.txt
pythonOps-0.1.4.dist-info/top_level.txt
pythonOps-0.1.4.dist-info/RECORD
